aiochris_oag/__init__.py
aiochris_oag/api_client.py
aiochris_oag/api_response.py
aiochris_oag/configuration.py
aiochris_oag/exceptions.py
aiochris_oag/py.typed
aiochris_oag/rest.py
aiochris_oag/api/__init__.py
aiochris_oag/api/auth_token_api.py
aiochris_oag/api/chris_admin_api.py
aiochris_oag/api/chrisinstance_api.py
aiochris_oag/api/comments_api.py
aiochris_oag/api/computeresources_api.py
aiochris_oag/api/default_api.py
aiochris_oag/api/downloadtokens_api.py
aiochris_oag/api/filebrowser_api.py
aiochris_oag/api/grouppermissions_api.py
aiochris_oag/api/groups_api.py
aiochris_oag/api/note_api.py
aiochris_oag/api/pacs_api.py
aiochris_oag/api/pipelines_api.py
aiochris_oag/api/plugininstances_api.py
aiochris_oag/api/plugins_api.py
aiochris_oag/api/publicfeeds_api.py
aiochris_oag/api/schema_api.py
aiochris_oag/api/search_api.py
aiochris_oag/api/taggings_api.py
aiochris_oag/api/tags_api.py
aiochris_oag/api/userfiles_api.py
aiochris_oag/api/userpermissions_api.py
aiochris_oag/api/users_api.py
aiochris_oag/models/__init__.py
aiochris_oag/models/auth_token.py
aiochris_oag/models/auth_token_request.py
aiochris_oag/models/blank_enum.py
aiochris_oag/models/bool_parameter.py
aiochris_oag/models/chris_instance.py
aiochris_oag/models/comment.py
aiochris_oag/models/comment_request.py
aiochris_oag/models/compute_resource.py
aiochris_oag/models/compute_resource_request.py
aiochris_oag/models/default_piping_bool_parameter.py
aiochris_oag/models/default_piping_bool_parameter_request.py
aiochris_oag/models/default_piping_float_parameter.py
aiochris_oag/models/default_piping_float_parameter_request.py
aiochris_oag/models/default_piping_int_parameter.py
aiochris_oag/models/default_piping_int_parameter_request.py
aiochris_oag/models/default_piping_str_parameter.py
aiochris_oag/models/default_piping_str_parameter_request.py
aiochris_oag/models/feed.py
aiochris_oag/models/feed_group_permission.py
aiochris_oag/models/feed_group_permission_request.py
aiochris_oag/models/feed_request.py
aiochris_oag-0.0.1.dist-info/METADATA
aiochris_oag-0.0.1.dist-info/WHEEL
aiochris_oag-0.0.1.dist-info/top_level.txt
aiochris_oag-0.0.1.dist-info/RECORD
